helloworldtockenpackage/__init__.py
helloworldtockenpackage/helloworld.py
helloworldtokenpackage-0.0.5.dist-info/LICENSE.txt
helloworldtokenpackage-0.0.5.dist-info/METADATA
helloworldtokenpackage-0.0.5.dist-info/WHEEL
helloworldtokenpackage-0.0.5.dist-info/top_level.txt
helloworldtokenpackage-0.0.5.dist-info/RECORD
